periphery/__init__.py
periphery/__init__.pyi
periphery/gpio.py
periphery/gpio.pyi
periphery/gpio_cdev1.py
periphery/gpio_cdev2.py
periphery/gpio_sysfs.py
periphery/i2c.py
periphery/i2c.pyi
periphery/led.py
periphery/led.pyi
periphery/mmio.py
periphery/mmio.pyi
periphery/pwm.py
periphery/pwm.pyi
periphery/py.typed
periphery/serial.py
periphery/serial.pyi
periphery/spi.py
periphery/spi.pyi
python_periphery-2.4.0.dist-info/LICENSE
python_periphery-2.4.0.dist-info/METADATA
python_periphery-2.4.0.dist-info/WHEEL
python_periphery-2.4.0.dist-info/top_level.txt
python_periphery-2.4.0.dist-info/RECORD
